{
  "PERSONAL": {
    "glob": false,
    "Documentation": {
      "cat": [{ "glob": false }],
      "Identidity": {
        "subcat": [{ "glob": true, "word": "Personal ID", "vars": ["Passport", "License", "ID Card", "Your Name"] }],
        "key": []
      },
      "Hosehold": {
        "subcat": [{ "glob": false, "word": "Household Items", "vars": [] }],
        "key": []
      }
    },
    "Personal Gallery": {
      "cat": [{ "glob": false }],
      "Family": {
        "subcat": [{ "glob": false, "word": "Family Photos", "vars": [] }],
        "key": []
      },
      "Travels": {
        "subcat": [{ "glob": false, "word": "Travel Photos", "vars": [] }],
        "key": []
      }
    }
  },
  "WORK": {
    "glob": false,
    "Documentation": {
      "cat": [{ "glob": true }],
      "Incident Reports": {
        "subcat": [{ "glob": false, "word": "Incidents", "vars": ["Hardware Failure", "Software Bug", "Network Outage", "User Error"] }],
        "key": []
      },
      "Maintenance Logs": {
        "subcat": [{ "glob": false, "word": "Maintenance", "vars": ["Scheduled Check", "Firmware Update", "Driver Install", "Thermal Inspection", "Security Audit"] }],
        "key": []
      },
      "Client Profiles": {
        "subcat": [{ "glob": true, "word": "Client Info", "vars": ["Company Name", "Contact Info", "Device Inventory", "Service History"] }],
        "key": []
      }
    },
    "Software Tools": {
      "cat": [{ "glob": false }],
      "Diagnostic Tools": {
        "subcat": [{ "glob": true, "word": "Diagnostics", "vars": ["Procmon", "Sysmon", "Wireshark", "PowerShell", "Diagnostic"] }],
        "key": []
      },
      "Remote Support SS": {
        "subcat": [{ "glob": true, "word": "Remote Tools", "vars": ["TeamViewer", "AnyDesk", "Remote Support", "Screenshot"] }],
        "key": []
      }
    }
  },
  "COLLEGE": {
    "glob": false,
    "Courses": {
      "cat": [{ "glob": false }],
      "Statistics": {
        "subcat": [{ "glob": false, "word": "Stats Topics", "vars": ["Probability", "Regression", "Hypothesis Testing", "Bayesian Methods"] }],
        "key": []
      },
      "Machine Learning": {
        "subcat": [{ "glob": true, "word": "ML Topics", "vars": ["Supervised Learning", "Unsupervised Learning", "Neural Networks", "Model Evaluation"] }],
        "key": []
      }
    },
    "Tools": {
      "cat": [{ "glob": false }],
      "Programming": {
        "subcat": [{ "glob": true, "word": "Languages", "vars": ["Python", "R", "SQL", "Julia"] }],
        "key": []
      },
      "Libraries": {
        "subcat": [{ "glob": false, "word": "Data Science Libs", "vars": ["Pandas", "NumPy", "Scikit-learn", "TensorFlow"] }],
        "key": []
      }
    },
    "Projects": {
      "cat": [{ "glob": false }],
      "Data Analysis": {
        "subcat": [{ "glob": false, "word": "Analysis Types", "vars": ["Survey Data", "Financial Data", "Health Data", "Social Media Data"] }],
        "key": []
      },
      "Capstone": {
        "subcat": [{ "glob": true, "word": "Capstone Projects", "vars": ["Predictive Model", "Recommendation System", "Classification Task", "Visualization Dashboard"] }],
        "key": []
      }
    }
  },
  "HOBBIES": {
    "glob": false,
    "Steam Games": {
      "cat": [{ "glob": false }],
      "Blue Archive": {
        "subcat": [{ "glob": false, "word": "BA Content", "vars": ["Story Mode", "Character Collection", "Events", "PvP"] }],
        "key": []
      },
      "Counter-Strike 2": {
        "subcat": [{ "glob": false, "word": "CS2 Modes", "vars": ["Competitive", "Casual", "Deathmatch", "Workshop Maps"] }],
        "key": []
      }
    }
  }
}
